stochPathSim/__init__.py
stochPathSim/bdt_model.py
stochPathSim/black_scholes.py
stochPathSim/cir.py
stochPathSim/gbm.py
stochPathSim/heston_model.py
stochPathSim/ho_lee_model.py
stochPathSim/hull_white.py
stochPathSim/statistics_utils.py
stochPathSim/vasicek.py
stochastic_models/__init__.py
stochastic_models/bdt_model.py
stochastic_models/black_scholes.py
stochastic_models/cir.py
stochastic_models/gbm.py
stochastic_models/heston_model.py
stochastic_models/ho_lee_model.py
stochastic_models/hull_white.py
stochastic_models/vasicek.py
tests/__init__.py
tests/test_bdt_model.py
tests/test_black_scholes.py
tests/test_cir.py
tests/test_gbm.py
tests/test_heston_model.py
tests/test_ho_lee_model.py
tests/test_hull_white.py
tests/test_vasicek.py
stochPathSim-1.1.1.dist-info/METADATA
stochPathSim-1.1.1.dist-info/WHEEL
stochPathSim-1.1.1.dist-info/top_level.txt
stochPathSim-1.1.1.dist-info/RECORD
