Metadata-Version: 2.1
Name: stochPathSim
Version: 1.1.1
Summary: A Python library for stochastic modeling and simulations.
Home-page: https://github.com/AIM-IT4/stochPathSim
Author: Amit Kumar Jha
Author-email: jha.8@iitj.ac.in
Classifier: Programming Language :: Python :: 3
Classifier: License :: OSI Approved :: MIT License
Classifier: Operating System :: OS Independent
Requires-Python: >=3.6
Requires-Dist: numpy>=1.20.0
Requires-Dist: pandas>=1.2.0
Requires-Dist: matplotlib>=3.3.0
Requires-Dist: plotly>=5.0.0
